{
    "key": "group_645aa5cdd83b3",
    "title": "Large Quote",
    "fields": [
        {
            "key": "field_645aa5ce1e234",
            "label": "Person",
            "name": "person",
            "aria-label": "",
            "type": "post_object",
            "instructions": "",
            "required": 0,
            "conditional_logic": 0,
            "wrapper": {
                "width": "",
                "class": "",
                "id": ""
            },
            "post_type": [
                "team-members"
            ],
            "post_status": "",
            "taxonomy": "",
            "return_format": "id",
            "multiple": 0,
            "allow_null": 0,
            "ui": 1
        },
        {
            "key": "field_645aa6901e235",
            "label": "Custom image",
            "name": "custom_image",
            "aria-label": "",
            "type": "image",
            "instructions": "Use this to overwrite the image from the Team Member's post.",
            "required": 0,
            "conditional_logic": 0,
            "wrapper": {
                "width": "",
                "class": "",
                "id": ""
            },
            "return_format": "array",
            "library": "all",
            "min_width": "",
            "min_height": "",
            "min_size": "",
            "max_width": "",
            "max_height": "",
            "max_size": "",
            "mime_types": "",
            "preview_size": "medium"
        },
        {
            "key": "field_645aa6bb1e236",
            "label": "Quote",
            "name": "quote",
            "aria-label": "",
            "type": "text",
            "instructions": "No need to include opening or closing quotation marks, they will be added automatically.",
            "required": 0,
            "conditional_logic": 0,
            "wrapper": {
                "width": "",
                "class": "",
                "id": ""
            },
            "default_value": "",
            "maxlength": "",
            "placeholder": "Outside of Charlie Health, behavioral health treatment is mostly one-size-fits-all...",
            "prepend": "“",
            "append": "”"
        },
        {
            "key": "field_645aa7811e237",
            "label": "Reverse direction",
            "name": "direction",
            "aria-label": "",
            "type": "true_false",
            "instructions": "",
            "required": 0,
            "conditional_logic": 0,
            "wrapper": {
                "width": "",
                "class": "",
                "id": ""
            },
            "message": "",
            "default_value": 0,
            "ui_on_text": "Image left",
            "ui_off_text": "Image right",
            "ui": 1
        }
    ],
    "location": [
        [
            {
                "param": "block",
                "operator": "==",
                "value": "acf\/large-quote-block"
            }
        ]
    ],
    "menu_order": 0,
    "position": "normal",
    "style": "default",
    "label_placement": "top",
    "instruction_placement": "label",
    "hide_on_screen": "",
    "active": true,
    "description": "",
    "show_in_rest": 0,
    "modified": 1683664488
}