{
    "key": "post_type_644827e3d4191",
    "title": "Outreach Team Members",
    "menu_order": 0,
    "active": true,
    "post_type": "outreach-team-member",
    "advanced_configuration": true,
    "import_source": "",
    "import_date": "",
    "labels": {
        "name": "Outreach Team Members",
        "singular_name": "Outreach Team Member",
        "menu_name": "Outreach Team Members",
        "all_items": "All Outreach Team Members",
        "edit_item": "Edit Outreach Team Member",
        "view_item": "View Outreach Team Member",
        "view_items": "View Outreach Team Members",
        "add_new_item": "Add New Outreach Team Member",
        "add_new": "",
        "new_item": "New Outreach Team Member",
        "parent_item_colon": "Parent Outreach Team Member:",
        "search_items": "Search Outreach Team Members",
        "not_found": "No outreach team members found",
        "not_found_in_trash": "No outreach team members found in Trash",
        "archives": "Outreach Team Member Archives",
        "attributes": "Outreach Team Member Attributes",
        "featured_image": "",
        "set_featured_image": "",
        "remove_featured_image": "",
        "use_featured_image": "",
        "insert_into_item": "Insert into outreach team member",
        "uploaded_to_this_item": "Uploaded to this outreach team member",
        "filter_items_list": "Filter outreach team members list",
        "filter_by_date": "Filter outreach team members by date",
        "items_list_navigation": "Outreach Team Members list navigation",
        "items_list": "Outreach Team Members list",
        "item_published": "Outreach Team Member published.",
        "item_published_privately": "Outreach Team Member published privately.",
        "item_reverted_to_draft": "Outreach Team Member reverted to draft.",
        "item_scheduled": "Outreach Team Member scheduled.",
        "item_updated": "Outreach Team Member updated.",
        "item_link": "Outreach Team Member Link",
        "item_link_description": "A link to a outreach team member."
    },
    "description": "",
    "public": true,
    "hierarchical": false,
    "exclude_from_search": true,
    "publicly_queryable": true,
    "show_ui": true,
    "show_in_menu": true,
    "admin_menu_parent": "",
    "show_in_admin_bar": true,
    "show_in_nav_menus": true,
    "show_in_rest": true,
    "rest_base": "",
    "rest_namespace": "wp\/v2",
    "rest_controller_class": "WP_REST_Posts_Controller",
    "menu_position": "",
    "menu_icon": "",
    "rename_capabilities": false,
    "singular_capability_name": "post",
    "plural_capability_name": "posts",
    "supports": [
        "title"
    ],
    "taxonomies": "",
    "has_archive": false,
    "has_archive_slug": "",
    "rewrite": {
        "permalink_rewrite": "post_type_key",
        "with_front": "1",
        "feeds": "0",
        "pages": "1"
    },
    "query_var": "post_type_key",
    "query_var_name": "",
    "can_export": true,
    "delete_with_user": false,
    "register_meta_box_cb": "",
    "modified": 1682450775
}